<skeleton>
	<bones>
		<bone id="0" name="Bone.001">
			<position x="0.000000" y="0.000000" z="0.000000"/>
			<rotation angle="0.895775">
				<axis x="-0.000000" y="-0.000000" z="-1.000000"/>
			</rotation>
		</bone>
		<bone id="1" name="Bone.002">
			<position x="0.000000" y="0.000000" z="0.000000"/>
			<rotation angle="0.000000">
				<axis x="-1.000000" y="0.000000" z="0.000000"/>
			</rotation>
		</bone>
		<bone id="2" name="Bone">
			<position x="0.000000" y="0.000000" z="0.000000"/>
			<rotation angle="0.900053">
				<axis x="-0.000000" y="0.000000" z="1.000000"/>
			</rotation>
		</bone>
	</bones>
	<bonehierarchy>
	</bonehierarchy>
	<animations>
		<animation name="action" length="1.600000">
			<tracks>
				<track bone="Bone.001">
					<keyframes>
						<keyframe time="0.000000">
							<translate x="0.000000" y="0.000000" z="0.000000"/>
							<rotate angle="0.000000">
								<axis x="0.000000" y="-0.000000" z="1.000000"/>
							</rotate>
							<scale x="1.000000" y="1.000000" z="1.000000"/>
						</keyframe>
						<keyframe time="0.040000">
							<translate x="0.000000" y="0.000000" z="0.000000"/>
							<rotate angle="0.015192">
								<axis x="-0.000000" y="0.000000" z="-1.000000"/>
							</rotate>
							<scale x="1.000000" y="1.000000" z="1.000000"/>
						</keyframe>
						<keyframe time="0.080000">
							<translate x="0.000000" y="0.000000" z="0.000000"/>
							<rotate angle="0.061160">
								<axis x="-0.000000" y="0.000000" z="-1.000000"/>
							</rotate>
							<scale x="1.000000" y="1.000000" z="1.000000"/>
						</keyframe>
						<keyframe time="0.120000">
							<translate x="0.000000" y="0.000000" z="0.000000"/>
							<rotate angle="0.136510">
								<axis x="-0.000000" y="0.000000" z="-1.000000"/>
							</rotate>
							<scale x="1.000000" y="1.000000" z="1.000000"/>
						</keyframe>
						<keyframe time="0.160000">
							<translate x="0.000000" y="0.000000" z="0.000000"/>
							<rotate angle="0.235917">
								<axis x="-0.000000" y="0.000000" z="-1.000000"/>
							</rotate>
							<scale x="1.000000" y="1.000000" z="1.000000"/>
						</keyframe>
						<keyframe time="0.200000">
							<translate x="0.000000" y="0.000000" z="0.000000"/>
							<rotate angle="0.349155">
								<axis x="-0.000000" y="0.000000" z="-1.000000"/>
							</rotate>
							<scale x="1.000000" y="1.000000" z="1.000000"/>
						</keyframe>
						<keyframe time="0.240000">
							<translate x="0.000000" y="0.000000" z="0.000000"/>
							<rotate angle="0.462374">
								<axis x="-0.000000" y="0.000000" z="-1.000000"/>
							</rotate>
							<scale x="1.000000" y="1.000000" z="1.000000"/>
						</keyframe>
						<keyframe time="0.280000">
							<translate x="0.000000" y="0.000000" z="0.000000"/>
							<rotate angle="0.561735">
								<axis x="-0.000000" y="0.000000" z="-1.000000"/>
							</rotate>
							<scale x="1.000000" y="1.000000" z="1.000000"/>
						</keyframe>
						<keyframe time="0.320000">
							<translate x="0.000000" y="0.000000" z="0.000000"/>
							<rotate angle="0.637027">
								<axis x="-0.000000" y="0.000000" z="-1.000000"/>
							</rotate>
							<scale x="1.000000" y="1.000000" z="1.000000"/>
						</keyframe>
						<keyframe time="0.360000">
							<translate x="0.000000" y="0.000000" z="0.000000"/>
							<rotate angle="0.682947">
								<axis x="-0.000000" y="0.000000" z="-1.000000"/>
							</rotate>
							<scale x="1.000000" y="1.000000" z="1.000000"/>
						</keyframe>
						<keyframe time="0.400000">
							<translate x="0.000000" y="0.000000" z="0.000000"/>
							<rotate angle="0.698131">
								<axis x="-0.000000" y="0.000000" z="-1.000000"/>
							</rotate>
							<scale x="1.000000" y="1.000000" z="1.000000"/>
						</keyframe>
						<keyframe time="0.440000">
							<translate x="0.001646" y="-0.000016" z="0.000000"/>
							<rotate angle="0.695810">
								<axis x="-0.000000" y="0.000000" z="-1.000000"/>
							</rotate>
							<scale x="1.000000" y="1.000000" z="1.000000"/>
						</keyframe>
						<keyframe time="0.480000">
							<translate x="0.006612" y="-0.000065" z="0.000000"/>
							<rotate angle="0.688796">
								<axis x="-0.000000" y="0.000000" z="-1.000000"/>
							</rotate>
							<scale x="1.000000" y="1.000000" z="1.000000"/>
						</keyframe>
						<keyframe time="0.520000">
							<translate x="0.014929" y="-0.000146" z="0.000000"/>
							<rotate angle="0.677022">
								<axis x="-0.000000" y="0.000000" z="-1.000000"/>
							</rotate>
							<scale x="1.000000" y="1.000000" z="1.000000"/>
						</keyframe>
						<keyframe time="0.560000">
							<translate x="0.026600" y="-0.000261" z="0.000000"/>
							<rotate angle="0.660443">
								<axis x="-0.000000" y="0.000000" z="-1.000000"/>
							</rotate>
							<scale x="1.000000" y="1.000000" z="1.000000"/>
						</keyframe>
						<keyframe time="0.600000">
							<translate x="0.041598" y="-0.000408" z="0.000000"/>
							<rotate angle="0.639046">
								<axis x="-0.000000" y="0.000000" z="-1.000000"/>
							</rotate>
							<scale x="1.000000" y="1.000000" z="1.000000"/>
						</keyframe>
						<keyframe time="0.640000">
							<translate x="0.059859" y="-0.000587" z="0.000000"/>
							<rotate angle="0.612856">
								<axis x="-0.000000" y="0.000000" z="-1.000000"/>
							</rotate>
							<scale x="1.000000" y="1.000000" z="1.000000"/>
						</keyframe>
						<keyframe time="0.680000">
							<translate x="0.081275" y="-0.000797" z="0.000000"/>
							<rotate angle="0.581958">
								<axis x="-0.000000" y="0.000000" z="-1.000000"/>
							</rotate>
							<scale x="1.000000" y="1.000000" z="1.000000"/>
						</keyframe>
						<keyframe time="0.720000">
							<translate x="0.105694" y="-0.001036" z="0.000000"/>
							<rotate angle="0.546505">
								<axis x="-0.000000" y="0.000000" z="-1.000000"/>
							</rotate>
							<scale x="1.000000" y="1.000000" z="1.000000"/>
						</keyframe>
						<keyframe time="0.760000">
							<translate x="0.132908" y="-0.001304" z="0.000000"/>
							<rotate angle="0.506736">
								<axis x="-0.000000" y="0.000000" z="-1.000000"/>
							</rotate>
							<scale x="1.000000" y="1.000000" z="1.000000"/>
						</keyframe>
						<keyframe time="0.800000">
							<translate x="0.162659" y="-0.001596" z="0.000000"/>
							<rotate angle="0.462984">
								<axis x="-0.000000" y="0.000000" z="-1.000000"/>
							</rotate>
							<scale x="1.000000" y="1.000000" z="1.000000"/>
						</keyframe>
						<keyframe time="0.840000">
							<translate x="0.194629" y="-0.001909" z="0.000000"/>
							<rotate angle="0.415687">
								<axis x="-0.000000" y="0.000000" z="-1.000000"/>
							</rotate>
							<scale x="1.000000" y="1.000000" z="1.000000"/>
						</keyframe>
						<keyframe time="0.880000">
							<translate x="0.228452" y="-0.002241" z="0.000000"/>
							<rotate angle="0.365392">
								<axis x="-0.000000" y="0.000000" z="-1.000000"/>
							</rotate>
							<scale x="1.000000" y="1.000000" z="1.000000"/>
						</keyframe>
						<keyframe time="0.920000">
							<translate x="0.263710" y="-0.002588" z="0.000000"/>
							<rotate angle="0.312742">
								<axis x="-0.000000" y="0.000000" z="-1.000000"/>
							</rotate>
							<scale x="1.000000" y="1.000000" z="1.000000"/>
						</keyframe>
						<keyframe time="0.960000">
							<translate x="0.299950" y="-0.002943" z="0.000000"/>
							<rotate angle="0.258470">
								<axis x="-0.000000" y="0.000000" z="-1.000000"/>
							</rotate>
							<scale x="1.000000" y="1.000000" z="1.000000"/>
						</keyframe>
						<keyframe time="1.000000">
							<translate x="0.336687" y="-0.003304" z="0.000000"/>
							<rotate angle="0.203370">
								<axis x="-0.000000" y="0.000000" z="-1.000000"/>
							</rotate>
							<scale x="1.000000" y="1.000000" z="1.000000"/>
						</keyframe>
						<keyframe time="1.040000">
							<translate x="0.373425" y="-0.003664" z="0.000000"/>
							<rotate angle="0.148269">
								<axis x="-0.000000" y="0.000000" z="-1.000000"/>
							</rotate>
							<scale x="1.000000" y="1.000000" z="1.000000"/>
						</keyframe>
						<keyframe time="1.080000">
							<translate x="0.409666" y="-0.004020" z="0.000000"/>
							<rotate angle="0.093995">
								<axis x="-0.000000" y="0.000000" z="-1.000000"/>
							</rotate>
							<scale x="1.000000" y="1.000000" z="1.000000"/>
						</keyframe>
						<keyframe time="1.120000">
							<translate x="0.444926" y="-0.004366" z="0.000000"/>
							<rotate angle="0.041341">
								<axis x="-0.000000" y="-0.000000" z="-1.000000"/>
							</rotate>
							<scale x="1.000000" y="1.000000" z="1.000000"/>
						</keyframe>
						<keyframe time="1.160000">
							<translate x="0.478751" y="-0.004697" z="0.000000"/>
							<rotate angle="0.008950">
								<axis x="-0.000001" y="-0.000000" z="1.000000"/>
							</rotate>
							<scale x="1.000000" y="1.000000" z="1.000000"/>
						</keyframe>
						<keyframe time="1.200000">
							<translate x="0.510724" y="-0.005011" z="0.000000"/>
							<rotate angle="0.056254">
								<axis x="-0.000000" y="-0.000000" z="1.000000"/>
							</rotate>
							<scale x="1.000000" y="1.000000" z="1.000000"/>
						</keyframe>
						<keyframe time="1.240000">
							<translate x="0.540478" y="-0.005302" z="0.000000"/>
							<rotate angle="0.100012">
								<axis x="0.000000" y="-0.000000" z="1.000000"/>
							</rotate>
							<scale x="1.000000" y="1.000000" z="1.000000"/>
						</keyframe>
						<keyframe time="1.280000">
							<translate x="0.567696" y="-0.005569" z="0.000000"/>
							<rotate angle="0.139786">
								<axis x="0.000000" y="-0.000000" z="1.000000"/>
							</rotate>
							<scale x="1.000000" y="1.000000" z="1.000000"/>
						</keyframe>
						<keyframe time="1.320000">
							<translate x="0.592118" y="-0.005808" z="0.000000"/>
							<rotate angle="0.175244">
								<axis x="0.000000" y="-0.000000" z="1.000000"/>
							</rotate>
							<scale x="1.000000" y="1.000000" z="1.000000"/>
						</keyframe>
						<keyframe time="1.360000">
							<translate x="0.613537" y="-0.006017" z="0.000000"/>
							<rotate angle="0.206146">
								<axis x="0.000000" y="-0.000000" z="1.000000"/>
							</rotate>
							<scale x="1.000000" y="1.000000" z="1.000000"/>
						</keyframe>
						<keyframe time="1.400000">
							<translate x="0.631800" y="-0.006196" z="0.000000"/>
							<rotate angle="0.232340">
								<axis x="0.000000" y="-0.000000" z="1.000000"/>
							</rotate>
							<scale x="1.000000" y="1.000000" z="1.000000"/>
						</keyframe>
						<keyframe time="1.440000">
							<translate x="0.646801" y="-0.006342" z="0.000000"/>
							<rotate angle="0.253741">
								<axis x="0.000000" y="-0.000000" z="1.000000"/>
							</rotate>
							<scale x="1.000000" y="1.000000" z="1.000000"/>
						</keyframe>
						<keyframe time="1.480000">
							<translate x="0.658474" y="-0.006456" z="0.000000"/>
							<rotate angle="0.270322">
								<axis x="0.000000" y="-0.000000" z="1.000000"/>
							</rotate>
							<scale x="1.000000" y="1.000000" z="1.000000"/>
						</keyframe>
						<keyframe time="1.520000">
							<translate x="0.666793" y="-0.006537" z="0.000000"/>
							<rotate angle="0.282099">
								<axis x="0.000000" y="-0.000000" z="1.000000"/>
							</rotate>
							<scale x="1.000000" y="1.000000" z="1.000000"/>
						</keyframe>
						<keyframe time="1.560000">
							<translate x="0.671760" y="-0.006586" z="0.000000"/>
							<rotate angle="0.289114">
								<axis x="0.000000" y="-0.000000" z="1.000000"/>
							</rotate>
							<scale x="1.000000" y="1.000000" z="1.000000"/>
						</keyframe>
						<keyframe time="1.600000">
							<translate x="0.673406" y="-0.006602" z="0.000000"/>
							<rotate angle="0.291436">
								<axis x="0.000000" y="-0.000000" z="1.000000"/>
							</rotate>
							<scale x="1.000000" y="1.000000" z="1.000000"/>
						</keyframe>
					</keyframes>
				</track>
				<track bone="Bone.002">
					<keyframes>
						<keyframe time="0.000000">
							<translate x="0.000000" y="0.000000" z="0.000000"/>
							<rotate angle="0.000000">
								<axis x="1.000000" y="0.000000" z="0.000000"/>
							</rotate>
							<scale x="1.000000" y="1.000000" z="1.000000"/>
						</keyframe>
						<keyframe time="0.040000">
							<translate x="0.000065" y="-0.006581" z="0.000000"/>
							<rotate angle="0.000000">
								<axis x="1.000000" y="0.000000" z="0.000000"/>
							</rotate>
							<scale x="1.000000" y="1.000000" z="1.000000"/>
						</keyframe>
						<keyframe time="0.080000">
							<translate x="0.000259" y="-0.026427" z="0.000000"/>
							<rotate angle="0.000000">
								<axis x="1.000000" y="0.000000" z="0.000000"/>
							</rotate>
							<scale x="1.000000" y="1.000000" z="1.000000"/>
						</keyframe>
						<keyframe time="0.120000">
							<translate x="0.000585" y="-0.059628" z="0.000000"/>
							<rotate angle="0.000000">
								<axis x="1.000000" y="0.000000" z="0.000000"/>
							</rotate>
							<scale x="1.000000" y="1.000000" z="1.000000"/>
						</keyframe>
						<keyframe time="0.160000">
							<translate x="0.001043" y="-0.106172" z="0.000000"/>
							<rotate angle="0.000000">
								<axis x="1.000000" y="0.000000" z="0.000000"/>
							</rotate>
							<scale x="1.000000" y="1.000000" z="1.000000"/>
						</keyframe>
						<keyframe time="0.200000">
							<translate x="0.001631" y="-0.165923" z="0.000000"/>
							<rotate angle="0.000000">
								<axis x="1.000000" y="0.000000" z="0.000000"/>
							</rotate>
							<scale x="1.000000" y="1.000000" z="1.000000"/>
						</keyframe>
						<keyframe time="0.240000">
							<translate x="0.002347" y="-0.238598" z="0.000000"/>
							<rotate angle="0.000000">
								<axis x="1.000000" y="0.000000" z="0.000000"/>
							</rotate>
							<scale x="1.000000" y="1.000000" z="1.000000"/>
						</keyframe>
						<keyframe time="0.280000">
							<translate x="0.003187" y="-0.323753" z="0.000000"/>
							<rotate angle="0.000000">
								<axis x="1.000000" y="0.000000" z="0.000000"/>
							</rotate>
							<scale x="1.000000" y="1.000000" z="1.000000"/>
						</keyframe>
						<keyframe time="0.320000">
							<translate x="0.004145" y="-0.420753" z="0.000000"/>
							<rotate angle="0.000000">
								<axis x="1.000000" y="0.000000" z="0.000000"/>
							</rotate>
							<scale x="1.000000" y="1.000000" z="1.000000"/>
						</keyframe>
						<keyframe time="0.360000">
							<translate x="0.005212" y="-0.528769" z="0.000000"/>
							<rotate angle="0.000000">
								<axis x="1.000000" y="0.000000" z="0.000000"/>
							</rotate>
							<scale x="1.000000" y="1.000000" z="1.000000"/>
						</keyframe>
						<keyframe time="0.400000">
							<translate x="0.006379" y="-0.646757" z="0.000000"/>
							<rotate angle="0.000000">
								<axis x="1.000000" y="0.000000" z="0.000000"/>
							</rotate>
							<scale x="1.000000" y="1.000000" z="1.000000"/>
						</keyframe>
						<keyframe time="0.440000">
							<translate x="0.007633" y="-0.773467" z="0.000000"/>
							<rotate angle="0.000000">
								<axis x="1.000000" y="0.000000" z="0.000000"/>
							</rotate>
							<scale x="1.000000" y="1.000000" z="1.000000"/>
						</keyframe>
						<keyframe time="0.480000">
							<translate x="0.008959" y="-0.907445" z="0.000000"/>
							<rotate angle="0.000000">
								<axis x="1.000000" y="0.000000" z="0.000000"/>
							</rotate>
							<scale x="1.000000" y="1.000000" z="1.000000"/>
						</keyframe>
						<keyframe time="0.520000">
							<translate x="0.010342" y="-1.047059" z="0.000000"/>
							<rotate angle="0.000000">
								<axis x="1.000000" y="0.000000" z="0.000000"/>
							</rotate>
							<scale x="1.000000" y="1.000000" z="1.000000"/>
						</keyframe>
						<keyframe time="0.560000">
							<translate x="0.011763" y="-1.190526" z="0.000000"/>
							<rotate angle="0.000000">
								<axis x="1.000000" y="0.000000" z="0.000000"/>
							</rotate>
							<scale x="1.000000" y="1.000000" z="1.000000"/>
						</keyframe>
						<keyframe time="0.600000">
							<translate x="0.013204" y="-1.335960" z="0.000000"/>
							<rotate angle="0.000000">
								<axis x="1.000000" y="0.000000" z="0.000000"/>
							</rotate>
							<scale x="1.000000" y="1.000000" z="1.000000"/>
						</keyframe>
						<keyframe time="0.640000">
							<translate x="0.014645" y="-1.481417" z="0.000000"/>
							<rotate angle="0.000000">
								<axis x="1.000000" y="0.000000" z="0.000000"/>
							</rotate>
							<scale x="1.000000" y="1.000000" z="1.000000"/>
						</keyframe>
						<keyframe time="0.680000">
							<translate x="0.016066" y="-1.624951" z="0.000000"/>
							<rotate angle="0.000000">
								<axis x="1.000000" y="0.000000" z="0.000000"/>
							</rotate>
							<scale x="1.000000" y="1.000000" z="1.000000"/>
						</keyframe>
						<keyframe time="0.720000">
							<translate x="0.017449" y="-1.764672" z="0.000000"/>
							<rotate angle="0.000000">
								<axis x="1.000000" y="0.000000" z="0.000000"/>
							</rotate>
							<scale x="1.000000" y="1.000000" z="1.000000"/>
						</keyframe>
						<keyframe time="0.760000">
							<translate x="0.018775" y="-1.898792" z="0.000000"/>
							<rotate angle="0.000000">
								<axis x="1.000000" y="0.000000" z="0.000000"/>
							</rotate>
							<scale x="1.000000" y="1.000000" z="1.000000"/>
						</keyframe>
						<keyframe time="0.800000">
							<translate x="0.020029" y="-2.025670" z="0.000000"/>
							<rotate angle="0.000000">
								<axis x="1.000000" y="0.000000" z="0.000000"/>
							</rotate>
							<scale x="1.000000" y="1.000000" z="1.000000"/>
						</keyframe>
						<keyframe time="0.840000">
							<translate x="0.021196" y="-2.143846" z="0.000000"/>
							<rotate angle="0.000000">
								<axis x="1.000000" y="0.000000" z="0.000000"/>
							</rotate>
							<scale x="1.000000" y="1.000000" z="1.000000"/>
						</keyframe>
						<keyframe time="0.880000">
							<translate x="0.022263" y="-2.252058" z="0.000000"/>
							<rotate angle="0.000000">
								<axis x="1.000000" y="0.000000" z="0.000000"/>
							</rotate>
							<scale x="1.000000" y="1.000000" z="1.000000"/>
						</keyframe>
						<keyframe time="0.920000">
							<translate x="0.023221" y="-2.349257" z="0.000000"/>
							<rotate angle="0.000000">
								<axis x="1.000000" y="0.000000" z="0.000000"/>
							</rotate>
							<scale x="1.000000" y="1.000000" z="1.000000"/>
						</keyframe>
						<keyframe time="0.960000">
							<translate x="0.024061" y="-2.434601" z="0.000000"/>
							<rotate angle="0.000000">
								<axis x="1.000000" y="0.000000" z="0.000000"/>
							</rotate>
							<scale x="1.000000" y="1.000000" z="1.000000"/>
						</keyframe>
						<keyframe time="1.000000">
							<translate x="0.024777" y="-2.507451" z="0.000000"/>
							<rotate angle="0.000000">
								<axis x="1.000000" y="0.000000" z="0.000000"/>
							</rotate>
							<scale x="1.000000" y="1.000000" z="1.000000"/>
						</keyframe>
						<keyframe time="1.040000">
							<translate x="0.025365" y="-2.567353" z="0.000000"/>
							<rotate angle="0.000000">
								<axis x="1.000000" y="0.000000" z="0.000000"/>
							</rotate>
							<scale x="1.000000" y="1.000000" z="1.000000"/>
						</keyframe>
						<keyframe time="1.080000">
							<translate x="0.025823" y="-2.614021" z="0.000000"/>
							<rotate angle="0.000000">
								<axis x="1.000000" y="0.000000" z="0.000000"/>
							</rotate>
							<scale x="1.000000" y="1.000000" z="1.000000"/>
						</keyframe>
						<keyframe time="1.120000">
							<translate x="0.026149" y="-2.647315" z="0.000000"/>
							<rotate angle="0.000000">
								<axis x="1.000000" y="0.000000" z="0.000000"/>
							</rotate>
							<scale x="1.000000" y="1.000000" z="1.000000"/>
						</keyframe>
						<keyframe time="1.160000">
							<translate x="0.026344" y="-2.667218" z="0.000000"/>
							<rotate angle="0.000000">
								<axis x="1.000000" y="0.000000" z="0.000000"/>
							</rotate>
							<scale x="1.000000" y="1.000000" z="1.000000"/>
						</keyframe>
						<keyframe time="1.200000">
							<translate x="0.026408" y="-2.673819" z="0.000000"/>
							<rotate angle="0.000000">
								<axis x="1.000000" y="0.000000" z="0.000000"/>
							</rotate>
							<scale x="1.000000" y="1.000000" z="1.000000"/>
						</keyframe>
						<keyframe time="1.240000">
							<translate x="0.025969" y="-2.607507" z="0.000000"/>
							<rotate angle="0.000000">
								<axis x="1.000000" y="0.000000" z="0.000000"/>
							</rotate>
							<scale x="1.000000" y="1.000000" z="1.000000"/>
						</keyframe>
						<keyframe time="1.280000">
							<translate x="0.024648" y="-2.410049" z="0.000000"/>
							<rotate angle="0.000000">
								<axis x="1.000000" y="0.000000" z="0.000000"/>
							</rotate>
							<scale x="1.000000" y="1.000000" z="1.000000"/>
						</keyframe>
						<keyframe time="1.320000">
							<translate x="0.022499" y="-2.091966" z="0.000000"/>
							<rotate angle="0.000000">
								<axis x="1.000000" y="0.000000" z="0.000000"/>
							</rotate>
							<scale x="1.000000" y="1.000000" z="1.000000"/>
						</keyframe>
						<keyframe time="1.360000">
							<translate x="0.019689" y="-1.677813" z="0.000000"/>
							<rotate angle="0.000000">
								<axis x="1.000000" y="0.000000" z="0.000000"/>
							</rotate>
							<scale x="1.000000" y="1.000000" z="1.000000"/>
						</keyframe>
						<keyframe time="1.400000">
							<translate x="0.016505" y="-1.207404" z="0.000000"/>
							<rotate angle="0.000000">
								<axis x="1.000000" y="0.000000" z="0.000000"/>
							</rotate>
							<scale x="1.000000" y="1.000000" z="1.000000"/>
						</keyframe>
						<keyframe time="1.440000">
							<translate x="0.013321" y="-0.731884" z="0.000000"/>
							<rotate angle="0.000000">
								<axis x="1.000000" y="0.000000" z="0.000000"/>
							</rotate>
							<scale x="1.000000" y="1.000000" z="1.000000"/>
						</keyframe>
						<keyframe time="1.480000">
							<translate x="0.010511" y="-0.304611" z="0.000000"/>
							<rotate angle="0.000000">
								<axis x="1.000000" y="0.000000" z="0.000000"/>
							</rotate>
							<scale x="1.000000" y="1.000000" z="1.000000"/>
						</keyframe>
						<keyframe time="1.520000">
							<translate x="0.008363" y="0.029233" z="-0.000000"/>
							<rotate angle="0.000000">
								<axis x="1.000000" y="0.000000" z="0.000000"/>
							</rotate>
							<scale x="1.000000" y="1.000000" z="1.000000"/>
						</keyframe>
						<keyframe time="1.560000">
							<translate x="0.007041" y="0.239187" z="-0.000000"/>
							<rotate angle="0.000000">
								<axis x="1.000000" y="0.000000" z="0.000000"/>
							</rotate>
							<scale x="1.000000" y="1.000000" z="1.000000"/>
						</keyframe>
						<keyframe time="1.600000">
							<translate x="0.006602" y="0.310295" z="-0.000000"/>
							<rotate angle="0.000000">
								<axis x="1.000000" y="0.000000" z="0.000000"/>
							</rotate>
							<scale x="1.000000" y="1.000000" z="1.000000"/>
						</keyframe>
					</keyframes>
				</track>
				<track bone="Bone">
					<keyframes>
						<keyframe time="0.000000">
							<translate x="0.000000" y="0.000000" z="0.000000"/>
							<rotate angle="0.000000">
								<axis x="0.000000" y="0.000000" z="-1.000000"/>
							</rotate>
							<scale x="1.000000" y="1.000000" z="1.000000"/>
						</keyframe>
						<keyframe time="0.040000">
							<translate x="0.000000" y="0.000000" z="0.000000"/>
							<rotate angle="0.003782">
								<axis x="-0.000000" y="-0.000000" z="1.000000"/>
							</rotate>
							<scale x="1.000000" y="1.000000" z="1.000000"/>
						</keyframe>
						<keyframe time="0.080000">
							<translate x="0.000000" y="0.000000" z="0.000000"/>
							<rotate angle="0.015192">
								<axis x="-0.000000" y="-0.000000" z="1.000000"/>
							</rotate>
							<scale x="1.000000" y="1.000000" z="1.000000"/>
						</keyframe>
						<keyframe time="0.120000">
							<translate x="0.000000" y="0.000000" z="0.000000"/>
							<rotate angle="0.034326">
								<axis x="-0.000000" y="-0.000000" z="1.000000"/>
							</rotate>
							<scale x="1.000000" y="1.000000" z="1.000000"/>
						</keyframe>
						<keyframe time="0.160000">
							<translate x="0.000000" y="0.000000" z="0.000000"/>
							<rotate angle="0.061125">
								<axis x="-0.000000" y="-0.000000" z="1.000000"/>
							</rotate>
							<scale x="1.000000" y="1.000000" z="1.000000"/>
						</keyframe>
						<keyframe time="0.200000">
							<translate x="0.000000" y="0.000000" z="0.000000"/>
							<rotate angle="0.095333">
								<axis x="-0.000000" y="-0.000000" z="1.000000"/>
							</rotate>
							<scale x="1.000000" y="1.000000" z="1.000000"/>
						</keyframe>
						<keyframe time="0.240000">
							<translate x="0.000000" y="0.000000" z="0.000000"/>
							<rotate angle="0.136445">
								<axis x="-0.000000" y="-0.000000" z="1.000000"/>
							</rotate>
							<scale x="1.000000" y="1.000000" z="1.000000"/>
						</keyframe>
						<keyframe time="0.280000">
							<translate x="0.000000" y="0.000000" z="0.000000"/>
							<rotate angle="0.183658">
								<axis x="-0.000000" y="-0.000000" z="1.000000"/>
							</rotate>
							<scale x="1.000000" y="1.000000" z="1.000000"/>
						</keyframe>
						<keyframe time="0.320000">
							<translate x="0.000000" y="0.000000" z="0.000000"/>
							<rotate angle="0.235841">
								<axis x="-0.000000" y="-0.000000" z="1.000000"/>
							</rotate>
							<scale x="1.000000" y="1.000000" z="1.000000"/>
						</keyframe>
						<keyframe time="0.360000">
							<translate x="0.000000" y="0.000000" z="0.000000"/>
							<rotate angle="0.291549">
								<axis x="-0.000000" y="-0.000000" z="1.000000"/>
							</rotate>
							<scale x="1.000000" y="1.000000" z="1.000000"/>
						</keyframe>
						<keyframe time="0.400000">
							<translate x="0.000000" y="0.000000" z="0.000000"/>
							<rotate angle="0.349087">
								<axis x="-0.000000" y="-0.000000" z="1.000000"/>
							</rotate>
							<scale x="1.000000" y="1.000000" z="1.000000"/>
						</keyframe>
						<keyframe time="0.440000">
							<translate x="0.000000" y="0.000000" z="0.000000"/>
							<rotate angle="0.406625">
								<axis x="-0.000000" y="-0.000000" z="1.000000"/>
							</rotate>
							<scale x="1.000000" y="1.000000" z="1.000000"/>
						</keyframe>
						<keyframe time="0.480000">
							<translate x="0.000000" y="0.000000" z="0.000000"/>
							<rotate angle="0.462329">
								<axis x="-0.000000" y="-0.000000" z="1.000000"/>
							</rotate>
							<scale x="1.000000" y="1.000000" z="1.000000"/>
						</keyframe>
						<keyframe time="0.520000">
							<translate x="0.000000" y="0.000000" z="0.000000"/>
							<rotate angle="0.514506">
								<axis x="-0.000000" y="-0.000000" z="1.000000"/>
							</rotate>
							<scale x="1.000000" y="1.000000" z="1.000000"/>
						</keyframe>
						<keyframe time="0.560000">
							<translate x="0.000000" y="0.000000" z="0.000000"/>
							<rotate angle="0.561713">
								<axis x="-0.000000" y="-0.000000" z="1.000000"/>
							</rotate>
							<scale x="1.000000" y="1.000000" z="1.000000"/>
						</keyframe>
						<keyframe time="0.600000">
							<translate x="0.000000" y="0.000000" z="0.000000"/>
							<rotate angle="0.602820">
								<axis x="-0.000000" y="-0.000000" z="1.000000"/>
							</rotate>
							<scale x="1.000000" y="1.000000" z="1.000000"/>
						</keyframe>
						<keyframe time="0.640000">
							<translate x="0.000000" y="0.000000" z="0.000000"/>
							<rotate angle="0.637021">
								<axis x="-0.000000" y="-0.000000" z="1.000000"/>
							</rotate>
							<scale x="1.000000" y="1.000000" z="1.000000"/>
						</keyframe>
						<keyframe time="0.680000">
							<translate x="0.000000" y="0.000000" z="0.000000"/>
							<rotate angle="0.663814">
								<axis x="-0.000000" y="-0.000000" z="1.000000"/>
							</rotate>
							<scale x="1.000000" y="1.000000" z="1.000000"/>
						</keyframe>
						<keyframe time="0.720000">
							<translate x="0.000000" y="0.000000" z="0.000000"/>
							<rotate angle="0.682947">
								<axis x="-0.000000" y="-0.000000" z="1.000000"/>
							</rotate>
							<scale x="1.000000" y="1.000000" z="1.000000"/>
						</keyframe>
						<keyframe time="0.760000">
							<translate x="0.000000" y="0.000000" z="0.000000"/>
							<rotate angle="0.694360">
								<axis x="-0.000000" y="-0.000000" z="1.000000"/>
							</rotate>
							<scale x="1.000000" y="1.000000" z="1.000000"/>
						</keyframe>
						<keyframe time="0.800000">
							<translate x="0.000000" y="0.000000" z="0.000000"/>
							<rotate angle="0.698132">
								<axis x="-0.000000" y="-0.000000" z="1.000000"/>
							</rotate>
							<scale x="1.000000" y="1.000000" z="1.000000"/>
						</keyframe>
						<keyframe time="0.840000">
							<translate x="-0.003675" y="-0.000145" z="0.000000"/>
							<rotate angle="0.692279">
								<axis x="-0.000000" y="-0.000000" z="1.000000"/>
							</rotate>
							<scale x="1.000000" y="1.000000" z="1.000000"/>
						</keyframe>
						<keyframe time="0.880000">
							<translate x="-0.014784" y="-0.000585" z="0.000000"/>
							<rotate angle="0.674529">
								<axis x="-0.000000" y="-0.000000" z="1.000000"/>
							</rotate>
							<scale x="1.000000" y="1.000000" z="1.000000"/>
						</keyframe>
						<keyframe time="0.920000">
							<translate x="-0.033357" y="-0.001321" z="0.000000"/>
							<rotate angle="0.644658">
								<axis x="-0.000000" y="-0.000000" z="1.000000"/>
							</rotate>
							<scale x="1.000000" y="1.000000" z="1.000000"/>
						</keyframe>
						<keyframe time="0.960000">
							<translate x="-0.059272" y="-0.002347" z="0.000000"/>
							<rotate angle="0.602595">
								<axis x="-0.000000" y="-0.000000" z="1.000000"/>
							</rotate>
							<scale x="1.000000" y="1.000000" z="1.000000"/>
						</keyframe>
						<keyframe time="1.000000">
							<translate x="-0.092207" y="-0.003652" z="0.000000"/>
							<rotate angle="0.548532">
								<axis x="-0.000000" y="0.000000" z="1.000000"/>
							</rotate>
							<scale x="1.000000" y="1.000000" z="1.000000"/>
						</keyframe>
						<keyframe time="1.040000">
							<translate x="-0.131602" y="-0.005213" z="0.000000"/>
							<rotate angle="0.483064">
								<axis x="-0.000000" y="0.000000" z="1.000000"/>
							</rotate>
							<scale x="1.000000" y="1.000000" z="1.000000"/>
						</keyframe>
						<keyframe time="1.080000">
							<translate x="-0.176633" y="-0.006997" z="0.000000"/>
							<rotate angle="0.407314">
								<axis x="-0.000000" y="0.000000" z="1.000000"/>
							</rotate>
							<scale x="1.000000" y="1.000000" z="1.000000"/>
						</keyframe>
						<keyframe time="1.120000">
							<translate x="-0.226201" y="-0.008961" z="0.000000"/>
							<rotate angle="0.323033">
								<axis x="-0.000000" y="0.000000" z="1.000000"/>
							</rotate>
							<scale x="1.000000" y="1.000000" z="1.000000"/>
						</keyframe>
						<keyframe time="1.160000">
							<translate x="-0.278960" y="-0.011052" z="0.000000"/>
							<rotate angle="0.232607">
								<axis x="-0.000000" y="0.000000" z="1.000000"/>
							</rotate>
							<scale x="1.000000" y="1.000000" z="1.000000"/>
						</keyframe>
						<keyframe time="1.200000">
							<translate x="-0.333368" y="-0.013208" z="0.000000"/>
							<rotate angle="0.138954">
								<axis x="-0.000000" y="0.000000" z="1.000000"/>
							</rotate>
							<scale x="1.000000" y="1.000000" z="1.000000"/>
						</keyframe>
						<keyframe time="1.240000">
							<translate x="-0.387777" y="-0.015363" z="0.000000"/>
							<rotate angle="0.045293">
								<axis x="-0.000000" y="0.000000" z="1.000000"/>
							</rotate>
							<scale x="1.000000" y="1.000000" z="1.000000"/>
						</keyframe>
						<keyframe time="1.280000">
							<translate x="-0.440541" y="-0.017453" z="0.000000"/>
							<rotate angle="0.045145">
								<axis x="0.000000" y="0.000000" z="-1.000000"/>
							</rotate>
							<scale x="1.000000" y="1.000000" z="1.000000"/>
						</keyframe>
						<keyframe time="1.320000">
							<translate x="-0.490118" y="-0.019417" z="0.000000"/>
							<rotate angle="0.129451">
								<axis x="0.000000" y="0.000000" z="-1.000000"/>
							</rotate>
							<scale x="1.000000" y="1.000000" z="1.000000"/>
						</keyframe>
						<keyframe time="1.360000">
							<translate x="-0.535159" y="-0.021200" z="0.000000"/>
							<rotate angle="0.205231">
								<axis x="0.000000" y="0.000000" z="-1.000000"/>
							</rotate>
							<scale x="1.000000" y="1.000000" z="1.000000"/>
						</keyframe>
						<keyframe time="1.400000">
							<translate x="-0.574565" y="-0.022759" z="0.000000"/>
							<rotate angle="0.270731">
								<axis x="0.000000" y="0.000000" z="-1.000000"/>
							</rotate>
							<scale x="1.000000" y="1.000000" z="1.000000"/>
						</keyframe>
						<keyframe time="1.440000">
							<translate x="-0.607510" y="-0.024063" z="0.000000"/>
							<rotate angle="0.324824">
								<axis x="0.000000" y="0.000000" z="-1.000000"/>
							</rotate>
							<scale x="1.000000" y="1.000000" z="1.000000"/>
						</keyframe>
						<keyframe time="1.480000">
							<translate x="-0.633434" y="-0.025089" z="0.000000"/>
							<rotate angle="0.366913">
								<axis x="0.000000" y="0.000000" z="-1.000000"/>
							</rotate>
							<scale x="1.000000" y="1.000000" z="1.000000"/>
						</keyframe>
						<keyframe time="1.520000">
							<translate x="-0.652014" y="-0.025823" z="0.000000"/>
							<rotate angle="0.396804">
								<axis x="0.000000" y="0.000000" z="-1.000000"/>
							</rotate>
							<scale x="1.000000" y="1.000000" z="1.000000"/>
						</keyframe>
						<keyframe time="1.560000">
							<translate x="-0.663127" y="-0.026263" z="0.000000"/>
							<rotate angle="0.414566">
								<axis x="0.000000" y="0.000000" z="-1.000000"/>
							</rotate>
							<scale x="1.000000" y="1.000000" z="1.000000"/>
						</keyframe>
						<keyframe time="1.600000">
							<translate x="-0.666804" y="-0.026408" z="0.000000"/>
							<rotate angle="0.420423">
								<axis x="0.000000" y="0.000000" z="-1.000000"/>
							</rotate>
							<scale x="1.000000" y="1.000000" z="1.000000"/>
						</keyframe>
					</keyframes>
				</track>
			</tracks>
		</animation>
	</animations>
</skeleton>
